vector_quantize_pytorch/__init__.py
vector_quantize_pytorch/binary_mapper.py
vector_quantize_pytorch/finite_scalar_quantization.py
vector_quantize_pytorch/latent_quantization.py
vector_quantize_pytorch/lookup_free_quantization.py
vector_quantize_pytorch/random_projection_quantizer.py
vector_quantize_pytorch/residual_fsq.py
vector_quantize_pytorch/residual_lfq.py
vector_quantize_pytorch/residual_sim_vq.py
vector_quantize_pytorch/residual_vq.py
vector_quantize_pytorch/sim_vq.py
vector_quantize_pytorch/utils.py
vector_quantize_pytorch/vector_quantize_pytorch.py
vector_quantize_pytorch-1.27.20.dist-info/METADATA
vector_quantize_pytorch-1.27.20.dist-info/WHEEL
vector_quantize_pytorch-1.27.20.dist-info/licenses/LICENSE
vector_quantize_pytorch-1.27.20.dist-info/RECORD
