Metadata-Version: 2.4
Name: vector-quantize-pytorch
Version: 1.27.20
Summary: Vector Quantization - Pytorch
Project-URL: Homepage, https://pypi.org/project/vector-quantize-pytorch/
Project-URL: Repository, https://github.com/lucidrains/vector-quantizer-pytorch
Author-email: Phil Wang <lucidrains@gmail.com>
License: MIT License
License-File: LICENSE
Keywords: artificial intelligence,deep learning,pytorch,quantization
Classifier: Development Status :: 4 - Beta
Classifier: Intended Audience :: Developers
Classifier: License :: OSI Approved :: MIT License
Classifier: Programming Language :: Python :: 3.6
Classifier: Topic :: Scientific/Engineering :: Artificial Intelligence
Requires-Python: >=3.9
Requires-Dist: einops>=0.8.0
Requires-Dist: einx>=0.3.0
Requires-Dist: torch>=2.4
Provides-Extra: examples
Requires-Dist: torchvision; extra == 'examples'
Requires-Dist: tqdm; extra == 'examples'
